transcription_mcp_server/__init__.py
transcription_mcp_server/server.py
transcription_mcp_server-0.1.5.dist-info/METADATA
transcription_mcp_server-0.1.5.dist-info/WHEEL
transcription_mcp_server-0.1.5.dist-info/entry_points.txt
transcription_mcp_server-0.1.5.dist-info/top_level.txt
transcription_mcp_server-0.1.5.dist-info/RECORD
